[
  {
    "Employee Count": 10,
    "TimeStamp": "2020-06-06T14:00:00.000Z",
    "Country": "India",
    "State": "Maharashtra",
    "City": "Pune",
    "DC": "SEZ",
    "Region": "Cafeteria 1",
    "Sub Region 1": "Floor 0",
    "Sub Region 2": "Dominos"
  },
  {
    "Employee Count": 15,
    "TimeStamp": "2020-06-06T14:00:00.000Z",
    "Sub Region 2": " KFC"
  },
  {
    "Employee Count": 20,
    "TimeStamp": "2020-06-06T14:00:00.000Z",
    "Country": "India",
    "State": "Maharashtra",
    "City": "Pune",
    "DC": "SEZ",
    "Region": "Cafeteria 1",
    "Sub Region 1": "Floor 1",
    "Sub Region 2": " Chennai Express"
  },
  {
    "Employee Count": 5,
    "TimeStamp": "2020-06-06T14:00:00.000Z",
    "Device": " ChaiPoint"
  },
  {
    "Employee Count": 0,
    "TimeStamp": "2020-06-06T14:00:00.000Z",
    "Country": "India",
    "State": "Maharashtra",
    "City": "Pune",
    "DC": "SEZ",
    "Region": "Cafeteria 1",
    "Sub Region 1": "Floor 0",
    "Sub Region 2": " Delhi Swad"
  },
  {
    "Employee Count": 23,
    "TimeStamp": "2020-06-06T14:00:00.000Z",
    "Country": "India",
    "State": "Maharashtra",
    "City": "Pune",
    "DC": "SEZ",
    "Region": "Cafeteria 1",
    "Sub Region 1": "Floor 0",
    "Device": " Common Area in Front of Dominos"
  },
  {
    "Employee Count": 6,
    "TimeStamp": "2020-06-06T14:00:00.000Z",
    "Country": "India",
    "State": "Maharashtra",
    "City": "Pune",
    "DC": "SEZ",
    "Region": "Cafeteria 1",
    "Sub Region 1": "Floor 0",
    "Sub Region 2": " Common Area in Front of KFC"
  },
  {
    "Employee Count": 17,
    "TimeStamp": "2020-06-06T14:00:00.000Z",
    "Sub Region 2": " Common Area in Front of Chennai Express"
  },
  {
    "Employee Count": 3,
    "TimeStamp": "2020-06-06T14:00:00.000Z",
    "Country": "India",
    "State": "Maharashtra",
    "City": "Pune",
    "DC": "SEZ",
    "Region": "Cafeteria 1",
    "Sub Region 1": "Floor 1",
    "Sub Region 2": " Common Area in Front of ChaiPoint"
  },
  {
    "Employee Count": 9,
    "TimeStamp": "2020-06-06T14:00:00.000Z",
    "Country": "India",
    "State": "Maharashtra",
    "City": "Pune",
    "DC": "SEZ",
    "Region": "Cafeteria 1",
    "Sub Region 1": "Floor 0",
    "Sub Region 2": " Common Area in Front of Delhi Swad"
  },
  {
    "Employee Count": 13,
    "TimeStamp": "2020-06-06T14:00:00.000Z",
    "Country": "India",
    "State": "Maharashtra",
    "City": "Pune",
    "DC": "SEZ",
    "Region": "Cafeteria 1",
    "Sub Region 1": "Floor 1",
    "Sub Region 2": " Common Area Right Wing"
  },
  {
    "Employee Count": 21,
    "TimeStamp": "2020-06-06T14:00:00.000Z",
    "Country": "India",
    "State": "Maharashtra",
    "City": "Pune",
    "DC": "SEZ",
    "Region": "Cafeteria 1",
    "Sub Region 1": "Floor 1",
    "Sub Region 2": " Common Area Left Wing"
  },
  {
    "Employee Count": 35,
    "TimeStamp": "2020-06-06T14:00:00.000Z",
    "Country": "India",
    "State": "Maharashtra",
    "City": "Pune",
    "DC": "SEZ",
    "Region": "Cafeteria 1",
    "Sub Region 1": "Floor 1",
    "Device": " Common Area Center Wing"
  }
]